taxi/__init__.py
taxi/aliases.py
taxi/exceptions.py
taxi/plugins.py
taxi/projects.py
taxi/settings.py
taxi/backends/__init__.py
taxi/backends/dummy.py
taxi/commands/__init__.py
taxi/commands/alias.py
taxi/commands/autofill.py
taxi/commands/base.py
taxi/commands/clean_aliases.py
taxi/commands/commit.py
taxi/commands/config.py
taxi/commands/current.py
taxi/commands/edit.py
taxi/commands/plugin.py
taxi/commands/project.py
taxi/commands/show.py
taxi/commands/start.py
taxi/commands/status.py
taxi/commands/stop.py
taxi/commands/types.py
taxi/commands/update.py
taxi/etc/taxirc.sample
taxi/timesheet/__init__.py
taxi/timesheet/entry.py
taxi/timesheet/flags.py
taxi/timesheet/lines.py
taxi/timesheet/parser.py
taxi/timesheet/timesheet.py
taxi/timesheet/utils.py
taxi/ui/__init__.py
taxi/ui/tty.py
taxi/utils/__init__.py
taxi/utils/date.py
taxi/utils/file.py
taxi/utils/structures.py
taxi/utils/terminal.py
taxi-6.3.1.dist-info/entry_points.txt
taxi-6.3.1.dist-info/LICENSE
taxi-6.3.1.dist-info/WHEEL
taxi-6.3.1.dist-info/METADATA
taxi-6.3.1.dist-info/RECORD
