Metadata-Version: 2.1
Name: taxi
Version: 6.3.1
Summary: Taxi: timesheeting made easy
Author-email: Sylvain Fankhauser <sephi@fhtagn.top>
Requires-Python: >=3.8
Requires-Dist: click>=3.3
Requires-Dist: appdirs>=1.4.0
Project-URL: Documentation, https://taxi-timesheets.readthedocs.io/
Project-URL: Source, https://github.com/sephii/taxi
